{
    "Ar36": {
        "error": 0.00021399841503468185,
        "error_type": "",
        "fit": "previous",
        "references": [
            {
                "exclude": false,
                "record_id": "ba-01-A-22434"
            }
        ],
        "value": 0.008689943807351668
    },
    "Ar37": {
        "error": 0.01013749074041996,
        "error_type": "",
        "fit": "previous",
        "references": [
            {
                "exclude": false,
                "record_id": "ba-01-A-22434"
            }
        ],
        "value": 0.06167589169947611
    },
    "Ar38": {
        "error": 0.010453077642819669,
        "error_type": "",
        "fit": "previous",
        "references": [
            {
                "exclude": false,
                "record_id": "ba-01-A-22434"
            }
        ],
        "value": 0.052613166926630144
    },
    "Ar39": {
        "error": 0.007779267141258271,
        "error_type": "",
        "fit": "previous",
        "references": [
            {
                "exclude": false,
                "record_id": "ba-01-A-22434"
            }
        ],
        "value": 0.09633141309381926
    },
    "Ar40": {
        "error": 0.025519878410921248,
        "error_type": "",
        "fit": "previous",
        "references": [
            {
                "exclude": false,
                "record_id": "ba-01-A-22434"
            }
        ],
        "value": 0.7908531260284793
    }
}